pytest_regtest/__init__.py
pytest_regtest/numpy_handler.py
pytest_regtest/pandas_handler.py
pytest_regtest/polars_handler.py
pytest_regtest/pytest_regtest.py
pytest_regtest/register_third_party_handlers.py
pytest_regtest/snapshot_handler.py
pytest_regtest/utils.py
pytest_regtest-2.3.3.dist-info/LICENSE.txt
pytest_regtest-2.3.3.dist-info/METADATA
pytest_regtest-2.3.3.dist-info/WHEEL
pytest_regtest-2.3.3.dist-info/entry_points.txt
pytest_regtest-2.3.3.dist-info/top_level.txt
pytest_regtest-2.3.3.dist-info/RECORD
