Metadata-Version: 2.1
Name: pytest-regtest
Version: 2.3.3
Summary: pytest plugin for snapshot regression testing
Author-email: Uwe Schmitt <uwe.schmitt@id.ethz.ch>
License: MIT License
Project-URL: Source, https://gitlab.com/uweschmitt/pytest-regtest
Project-URL: Documentation, https://pytest-regtest.readthedocs.org
Classifier: Intended Audience :: Developers
Classifier: Programming Language :: Python :: 3.9
Classifier: Programming Language :: Python :: 3.10
Classifier: Programming Language :: Python :: 3.11
Classifier: Programming Language :: Python :: 3.12
Classifier: License :: OSI Approved :: MIT License
License-File: LICENSE.txt
Requires-Dist: pytest >7.2
